{
    "event": {
        "link": "https://www.tapology.com/fightcenter/events/139670-ufc-fight-night",
        "date": "2026-04-18",
        "title": "UFC Fight Night: Burns vs. Malott"
    },
    "matchups": [
        {
            "fighters_raw": [
                {
                    "name": "gilbert burns",
                    "link": "https://www.tapology.com/fightcenter/fighters/31168-gilbert-burns-durinho"
                },
                {
                    "name": "mike malott",
                    "link": "https://www.tapology.com/fightcenter/fighters/22740-mike-malott"
                }
            ],
            "weight_class": 170,
            "rounds": 5,
            "isprelim": false
        },
        {
            "fighters_raw": [
                {
                    "name": "kyler phillips",
                    "link": "https://www.tapology.com/fightcenter/fighters/93501-kyler-phillips"
                },
                {
                    "name": "charles jourdain",
                    "link": "https://www.tapology.com/fightcenter/fighters/36724-charles-jourdain"
                }
            ],
            "weight_class": 135,
            "rounds": 3,
            "isprelim": false
        },
        {
            "fighters_raw": [
                {
                    "name": "mandel nallo",
                    "link": "https://www.tapology.com/fightcenter/fighters/24751-mandell-nallo"
                },
                {
                    "name": "jai herbert",
                    "link": "https://www.tapology.com/fightcenter/fighters/70002-jai-herbert"
                }
            ],
            "weight_class": 155,
            "rounds": 3,
            "isprelim": false
        },
        {
            "fighters_raw": [
                {
                    "name": "jasmine jasudavicius",
                    "link": "https://www.tapology.com/fightcenter/fighters/171056-jasmine-jasdavicious"
                },
                {
                    "name": "karine silva",
                    "link": "https://www.tapology.com/fightcenter/fighters/69225-karine-silva-killer"
                }
            ],
            "weight_class": 125,
            "rounds": 3,
            "isprelim": false
        },
        {
            "fighters_raw": [
                {
                    "name": "thiago moises",
                    "link": "https://www.tapology.com/fightcenter/fighters/49744-thiago-moiss"
                },
                {
                    "name": "gauge young",
                    "link": "https://www.tapology.com/fightcenter/fighters/213571-gauge-young"
                }
            ],
            "weight_class": 155,
            "rounds": 3,
            "isprelim": false
        },
        {
            "fighters_raw": [
                {
                    "name": "dennis buzukja",
                    "link": "https://www.tapology.com/fightcenter/fighters/131561-dennis-buzukia"
                },
                {
                    "name": "marcio barbosa",
                    "link": "https://www.tapology.com/fightcenter/fighters/126539-marcio-ticot"
                }
            ],
            "weight_class": 145,
            "rounds": 3,
            "isprelim": false
        },
        {
            "fighters_raw": [
                {
                    "name": "robert valentin",
                    "link": "https://www.tapology.com/fightcenter/fighters/136498-robert-valentin"
                },
                {
                    "name": "julien leblanc",
                    "link": "https://www.tapology.com/fightcenter/fighters/24714-julien-leblanc"
                }
            ],
            "weight_class": 185,
            "rounds": 3,
            "isprelim": true
        },
        {
            "fighters_raw": [
                {
                    "name": "tanner boser",
                    "link": "https://www.tapology.com/fightcenter/fighters/35149-tanner-boser"
                },
                {
                    "name": "gokhan saricam",
                    "link": "https://www.tapology.com/fightcenter/fighters/203358-gokhan-saricam"
                }
            ],
            "weight_class": 265,
            "rounds": 3,
            "isprelim": true
        },
        {
            "fighters_raw": [
                {
                    "name": "melissa croden",
                    "link": "https://www.tapology.com/fightcenter/fighters/140510-melissa-croden"
                },
                {
                    "name": "darya zheleznyakova",
                    "link": "https://www.tapology.com/fightcenter/fighters/229363-dariya-zheleznyakova"
                }
            ],
            "weight_class": 135,
            "rounds": 3,
            "isprelim": true
        },
        {
            "fighters_raw": [
                {
                    "name": "jj aldrich",
                    "link": "https://www.tapology.com/fightcenter/fighters/28420-jj-aldrich"
                },
                {
                    "name": "jamey-lyn horth",
                    "link": "https://www.tapology.com/fightcenter/fighters/148703-jamey-lyn-horth"
                }
            ],
            "weight_class": 125,
            "rounds": 3,
            "isprelim": true
        },
        {
            "fighters_raw": [
                {
                    "name": "mitch raposo",
                    "link": "https://www.tapology.com/fightcenter/fighters/160416-mitch-raposo"
                },
                {
                    "name": "allan nascimento",
                    "link": "https://www.tapology.com/fightcenter/fighters/30534-alan-nascimento"
                }
            ],
            "weight_class": 125,
            "rounds": 3,
            "isprelim": true
        },
        {
            "fighters_raw": [
                {
                    "name": "john castaneda",
                    "link": "https://www.tapology.com/fightcenter/fighters/20125-john-castaneda"
                },
                {
                    "name": "mark vologdin",
                    "link": "https://www.tapology.com/fightcenter/fighters/202598-mark-vologdin"
                }
            ],
            "weight_class": 135,
            "rounds": 3,
            "isprelim": true
        },
        {
            "fighters_raw": [
                {
                    "name": "jamie siraj",
                    "link": "https://www.tapology.com/fightcenter/fighters/35361-jamie-siraj-the-gremlin"
                },
                {
                    "name": "john yannis",
                    "link": "https://www.tapology.com/fightcenter/fighters/151617-john-yannies"
                }
            ],
            "weight_class": 145,
            "rounds": 3,
            "isprelim": true
        }
    ]
}